[
    {
        "id": "s1_103",
        "class": "\u03a3\u03c4",
        "description": "S1 \u2013 \u03a3\u03c4 \u03c4\u03ac\u03be\u03b7 \u2013 \u0395\u03c0\u03b1\u03bd\u03ac\u03bb\u03b7\u03c8\u03b7 \u03c4\u03b5\u03bb\u03b5\u03c5\u03c4\u03b1\u03af\u03bf \u03c3\u03b5\u03bd\u03ac\u03c1\u03b9\u03bf \u03c7\u03c1\u03bf\u03bd\u03b9\u03ac\u03c2",
        "shuffle_questions": "false",
        "send_score": "false",
        "allow_reset": "true",
        "shuffle_answers": "true"
    },
    {
        "question": "\u03a4\u03b9 \u03b2\u03bb\u03ad\u03c0\u03bf\u03c5\u03bc\u03b5 \u03c3\u03c4\u03b7\u03bd \u03b5\u03b9\u03ba\u03cc\u03bd\u03b1;",
        "image": "img5.png",
        "option0": "\u039a\u03bf\u03c5\u03bc\u03c0\u03af \u03c0\u03af\u03b5\u03c3\u03b7\u03c2",
        "option1": "\u03b1\u03b9\u03c3\u03b8\u03b7\u03c4\u03ae\u03c1\u03b1\u03c2 \u03c6\u03c9\u03c4\u03cc\u03c2",
        "option2": "neopixel led",
        "option3": "\u03c4\u03af\u03c0\u03bf\u03c4\u03b1 \u03b1\u03c0\u03cc \u03c4\u03b1 \u03c0\u03b1\u03c1\u03b1\u03c0\u03ac\u03bd\u03c9",
        "correct": "option0",
        "hint": null
    },
    {
        "question": "\u03a4\u03b9 \u03b2\u03bb\u03ad\u03c0\u03bf\u03c5\u03bc\u03b5 \u03c3\u03c4\u03b7\u03bd \u03b5\u03b9\u03ba\u03cc\u03bd\u03b1;",
        "image": "img6.png",
        "option0": "\u039a\u03bf\u03c5\u03bc\u03c0\u03af \u03c0\u03af\u03b5\u03c3\u03b7\u03c2",
        "option1": "\u03b1\u03b9\u03c3\u03b8\u03b7\u03c4\u03ae\u03c1\u03b1\u03c2 \u03c6\u03c9\u03c4\u03cc\u03c2",
        "option2": "neopixel led",
        "option3": "\u03c4\u03af\u03c0\u03bf\u03c4\u03b1 \u03b1\u03c0\u03cc \u03c4\u03b1 \u03c0\u03b1\u03c1\u03b1\u03c0\u03ac\u03bd\u03c9",
        "correct": "option2",
        "hint": null
    },
    {
        "question": "\u03a3\u03b5 \u03c0\u03bf\u03b9\u03bf pin \u03ad\u03c7\u03bf\u03c5\u03bc\u03b5 \u03c3\u03c5\u03bd\u03b4\u03ad\u03c3\u03b5\u03b9 \u03c4\u03bf \u03ba\u03bf\u03c5\u03bc\u03c0\u03af \u03c0\u03af\u03b5\u03c3\u03b7\u03c2",
        "image": "img0.png",
        "option0": "D6",
        "option1": "D5",
        "option2": "D7",
        "option3": "D8",
        "correct": "option0",
        "hint": null
    },
    {
        "question": "\u03a3\u03b5 \u03c0\u03bf\u03b9\u03bf pin \u03ad\u03c7\u03bf\u03c5\u03bc\u03b5 \u03c3\u03c5\u03bd\u03b4\u03ad\u03c3\u03b5\u03b9 \u03c4\u03bf neopixel led;",
        "image": "img0.png",
        "option0": "D9",
        "option1": "D8",
        "option2": "D7",
        "option3": "D6",
        "correct": "option0",
        "hint": null
    },
    {
        "question": "\u039c\u03b5\u03bb\u03ad\u03c4\u03b7\u03c3\u03b5 \u03c4\u03bf \u03c0\u03bb\u03b1\u03ba\u03af\u03b4\u03b9\u03bf \u03c4\u03b7\u03c2 \u03b5\u03b9\u03ba\u03cc\u03bd\u03b1\u03c2; \u03a0\u03bf\u03b9\u03b1 \u03b5\u03c0\u03b9\u03bb\u03bf\u03b3\u03ae \u03c0\u03c1\u03ad\u03c0\u03b5\u03b9 \u03bd\u03b1 \u03b4\u03b9\u03b1\u03bb\u03ad\u03be\u03bf\u03c5\u03bc\u03b5 \u03b3\u03b9\u03b1 \u03c4\u03bf \u03ba\u03bf\u03c5\u03bc\u03c0\u03af \u03c0\u03af\u03b5\u03c3\u03b7\u03c2;",
        "image": "img3.png",
        "option0": "D6",
        "option1": "D5",
        "option2": "D7",
        "option3": "D8",
        "correct": "option0",
        "hint": null
    },
    {
        "question": "\u039c\u03b5\u03bb\u03ad\u03c4\u03b7\u03c3\u03b5 \u03c4\u03bf \u03c0\u03bb\u03b1\u03ba\u03af\u03b4\u03b9\u03bf \u03c4\u03b7\u03c2 \u03b5\u03b9\u03ba\u03cc\u03bd\u03b1\u03c2; \u03a0\u03bf\u03b9\u03b1 \u03b5\u03c0\u03b9\u03bb\u03bf\u03b3\u03ae \u03c0\u03c1\u03ad\u03c0\u03b5\u03b9 \u03bd\u03b1 \u03b4\u03b9\u03b1\u03bb\u03ad\u03be\u03bf\u03c5\u03bc\u03b5 \u03b3\u03b9\u03b1 \u03c4\u03bf neopixel led?",
        "image": "img4.png",
        "option0": "D9",
        "option1": "D8",
        "option2": "D7",
        "option3": "D6",
        "correct": "option0",
        "hint": null
    },
    {
        "question": "\u03a4\u03b9 \u03bb\u03ac\u03b8\u03bf\u03c2 \u03ad\u03c7\u03b5\u03b9 \u03b3\u03af\u03bd\u03b5\u03b9 \u03c3\u03c4\u03bf \u03c3\u03b5\u03bd\u03ac\u03c1\u03b9\u03bf \u03c4\u03b7\u03c2 \u03b4\u03b9\u03c0\u03bb\u03b1\u03bd\u03ae\u03c2 \u03b5\u03b9\u03ba\u03cc\u03bd\u03b1\u03c2;",
        "image": "img7.png",
        "option0": "\u03a4\u03bf \u03ba\u03bf\u03c5\u03bc\u03c0\u03af \u03ba\u03b1\u03b9 \u03c4\u03bf led \u03ad\u03c7\u03bf\u03c5\u03bd \u03b4\u03b7\u03bb\u03c9\u03b8\u03b5\u03af \u03c3\u03c4\u03bf \u03af\u03b4\u03b9\u03bf pin",
        "option1": "\u0388\u03c7\u03b5\u03b9 \u03c7\u03c1\u03b7\u03c3\u03b9\u03bc\u03bf\u03c0\u03bf\u03b9\u03b7\u03b8\u03b5\u03af \u03bb\u03ac\u03b8\u03bf\u03c2 \u03c0\u03bb\u03b1\u03ba\u03af\u03b4\u03b9\u03bf \u03b5\u03bd\u03c4\u03bf\u03bb\u03ae\u03c2 \u03b3\u03b9\u03b1 \u03c4\u03bf \u03ba\u03bf\u03c5\u03bc\u03c0\u03af",
        "option2": "\u0388\u03c7\u03b5\u03b9 \u03c7\u03c1\u03b7\u03c3\u03b9\u03bc\u03bf\u03c0\u03bf\u03b9\u03b7\u03b8\u03b5\u03af \u03bb\u03ac\u03b8\u03bf\u03c2 \u03c0\u03bb\u03b1\u03ba\u03af\u03b4\u03b9\u03bf \u03b5\u03bd\u03c4\u03bf\u03bb\u03ae\u03c2 \u03b3\u03b9\u03b1 \u03c4\u03bf led neopixel",
        "option3": "\u0388\u03c7\u03b5\u03b9 \u03bf\u03c1\u03b9\u03c3\u03b8\u03b5\u03af \u03af\u03b4\u03b9\u03bf \u03c7\u03c1\u03ce\u03bc\u03b1 \u03ba\u03b1\u03b9 \u03b3\u03b9\u03b1 \u03c4\u03b7\u03bd \u03c0\u03b5\u03c1\u03af\u03c0\u03c4\u03c9\u03c3\u03b7 \u03c0\u03bf\u03c5 \u03b5\u03af\u03bd\u03b1\u03b9 \u03c0\u03b1\u03c4\u03b7\u03bc\u03ad\u03bd\u03bf \u03c4\u03bf \u03ba\u03bf\u03c5\u03bc\u03c0\u03af \u03c0\u03b1\u03c4\u03b7\u03bc\u03ad\u03bd\u03bf \u03ba\u03b1\u03b9 \u03b3\u03b9\u03b1 \u03c4\u03b7\u03bd \u03c0\u03b5\u03c1\u03af\u03c0\u03c4\u03c9\u03c3\u03b7 \u03c0\u03bf\u03c5 \u03b4\u03b5\u03bd \u03b5\u03af\u03bd\u03b1\u03b9 \u03c0\u03b1\u03c4\u03b7\u03bc\u03ad\u03bd\u03bf",
        "correct": "option0",
        "hint": null
    },
    {
        "question": "\u03a4\u03b9 \u03bb\u03ac\u03b8\u03bf\u03c2 \u03ad\u03c7\u03b5\u03b9 \u03b3\u03af\u03bd\u03b5\u03b9 \u03c3\u03c4\u03bf \u03c3\u03b5\u03bd\u03ac\u03c1\u03b9\u03bf \u03c4\u03b7\u03c2 \u03b4\u03b9\u03c0\u03bb\u03b1\u03bd\u03ae\u03c2 \u03b5\u03b9\u03ba\u03cc\u03bd\u03b1\u03c2;",
        "image": "img8.png",
        "option0": "\u0388\u03c7\u03b5\u03b9 \u03bf\u03c1\u03b9\u03c3\u03b8\u03b5\u03af \u03af\u03b4\u03b9\u03bf \u03c7\u03c1\u03ce\u03bc\u03b1 \u03ba\u03b1\u03b9 \u03b3\u03b9\u03b1 \u03c4\u03b7\u03bd \u03c0\u03b5\u03c1\u03af\u03c0\u03c4\u03c9\u03c3\u03b7 \u03c0\u03bf\u03c5 \u03b5\u03af\u03bd\u03b1\u03b9 \u03c0\u03b1\u03c4\u03b7\u03bc\u03ad\u03bd\u03bf \u03c4\u03bf \u03ba\u03bf\u03c5\u03bc\u03c0\u03af \u03c0\u03b1\u03c4\u03b7\u03bc\u03ad\u03bd\u03bf \u03ba\u03b1\u03b9 \u03b3\u03b9\u03b1 \u03c4\u03b7\u03bd \u03c0\u03b5\u03c1\u03af\u03c0\u03c4\u03c9\u03c3\u03b7 \u03c0\u03bf\u03c5 \u03b4\u03b5\u03bd \u03b5\u03af\u03bd\u03b1\u03b9 \u03c0\u03b1\u03c4\u03b7\u03bc\u03ad\u03bd\u03bf",
        "option1": "\u03a4\u03bf \u03ba\u03bf\u03c5\u03bc\u03c0\u03af \u03ba\u03b1\u03b9 \u03c4\u03bf led \u03ad\u03c7\u03bf\u03c5\u03bd \u03b4\u03b7\u03bb\u03c9\u03b8\u03b5\u03af \u03c3\u03c4\u03bf \u03af\u03b4\u03b9\u03bf pin",
        "option2": "\u0388\u03c7\u03b5\u03b9 \u03c7\u03c1\u03b7\u03c3\u03b9\u03bc\u03bf\u03c0\u03bf\u03b9\u03b7\u03b8\u03b5\u03af \u03bb\u03ac\u03b8\u03bf\u03c2 \u03c0\u03bb\u03b1\u03ba\u03af\u03b4\u03b9\u03bf \u03b5\u03bd\u03c4\u03bf\u03bb\u03ae\u03c2 \u03b3\u03b9\u03b1 \u03c4\u03bf led neopixel",
        "option3": "\u03a4\u03bf \u03ba\u03bf\u03c5\u03bc\u03c0\u03af \u03ba\u03b1\u03b9 \u03c4\u03bf led \u03ad\u03c7\u03bf\u03c5\u03bd \u03b4\u03b7\u03bb\u03c9\u03b8\u03b5\u03af \u03c3\u03c4\u03bf \u03af\u03b4\u03b9\u03bf pin",
        "correct": "option0",
        "hint": null
    },
    {
        "question": "\u03a4\u03b9 \u03bb\u03ac\u03b8\u03bf\u03c2 \u03ad\u03c7\u03b5\u03b9 \u03b3\u03af\u03bd\u03b5\u03b9 \u03c3\u03c4\u03bf \u03c3\u03b5\u03bd\u03ac\u03c1\u03b9\u03bf \u03c4\u03b7\u03c2 \u03b4\u03b9\u03c0\u03bb\u03b1\u03bd\u03ae\u03c2 \u03b5\u03b9\u03ba\u03cc\u03bd\u03b1\u03c2;",
        "image": "img9.png",
        "option0": "\u0394\u03b5\u03bd \u03ad\u03c7\u03b5\u03b9 \u03bc\u03c0\u03b5\u03b9 \u03c4\u03bf \u03ba\u03bf\u03bc\u03bc\u03ac\u03c4\u03b9 \u03b3\u03b9\u03b1 \u03c0\u03ac\u03bd\u03c4\u03b1",
        "option1": "\u03a4\u03bf \u03ba\u03bf\u03c5\u03bc\u03c0\u03af \u03ba\u03b1\u03b9 \u03c4\u03bf led \u03ad\u03c7\u03bf\u03c5\u03bd \u03b4\u03b7\u03bb\u03c9\u03b8\u03b5\u03af \u03c3\u03c4\u03bf \u03af\u03b4\u03b9\u03bf pin",
        "option2": "\u0388\u03c7\u03b5\u03b9 \u03bf\u03c1\u03b9\u03c3\u03b8\u03b5\u03af \u03af\u03b4\u03b9\u03bf \u03c7\u03c1\u03ce\u03bc\u03b1 \u03ba\u03b1\u03b9 \u03b3\u03b9\u03b1 \u03c4\u03b7\u03bd \u03c0\u03b5\u03c1\u03af\u03c0\u03c4\u03c9\u03c3\u03b7 \u03c0\u03bf\u03c5 \u03b5\u03af\u03bd\u03b1\u03b9 \u03c0\u03b1\u03c4\u03b7\u03bc\u03ad\u03bd\u03bf \u03c4\u03bf \u03ba\u03bf\u03c5\u03bc\u03c0\u03af \u03c0\u03b1\u03c4\u03b7\u03bc\u03ad\u03bd\u03bf \u03ba\u03b1\u03b9 \u03b3\u03b9\u03b1 \u03c4\u03b7\u03bd \u03c0\u03b5\u03c1\u03af\u03c0\u03c4\u03c9\u03c3\u03b7 \u03c0\u03bf\u03c5 \u03b4\u03b5\u03bd \u03b5\u03af\u03bd\u03b1\u03b9 \u03c0\u03b1\u03c4\u03b7\u03bc\u03ad\u03bd\u03bf",
        "option3": "\u0388\u03c7\u03b5\u03b9 \u03c7\u03c1\u03b7\u03c3\u03b9\u03bc\u03bf\u03c0\u03bf\u03b9\u03b7\u03b8\u03b5\u03af \u03bb\u03ac\u03b8\u03bf\u03c2 \u03c0\u03bb\u03b1\u03ba\u03af\u03b4\u03b9\u03bf \u03b5\u03bd\u03c4\u03bf\u03bb\u03ae\u03c2 \u03b3\u03b9\u03b1 \u03c4\u03bf \u03ba\u03bf\u03c5\u03bc\u03c0\u03af",
        "correct": "option0",
        "hint": null
    },
    {
        "question": "\u03a4\u03b9 \u03bb\u03ac\u03b8\u03bf\u03c2 \u03ad\u03c7\u03b5\u03b9 \u03b3\u03af\u03bd\u03b5\u03b9 \u03c3\u03c4\u03bf \u03c3\u03b5\u03bd\u03ac\u03c1\u03b9\u03bf \u03c4\u03b7\u03c2 \u03b4\u03b9\u03c0\u03bb\u03b1\u03bd\u03ae\u03c2 \u03b5\u03b9\u03ba\u03cc\u03bd\u03b1\u03c2;",
        "image": "img10.png",
        "option0": "\u0398\u03b1 \u03c0\u03c1\u03ad\u03c0\u03b5\u03b9 \u03bd\u03b1 \u03c7\u03c1\u03b7\u03c3\u03b9\u03bc\u03bf\u03c0\u03bf\u03b9\u03b7\u03b8\u03b5\u03af \u03c4\u03bf \u03ba\u03bf\u03c5\u03bc\u03c0\u03af \u03b5\u03ac\u03bd \u03b1\u03bb\u03bb\u03b9\u03ce\u03c2 \u03ba\u03b1\u03b9 \u03cc\u03c7\u03b9 \u03c4\u03bf \u03c3\u03ba\u03ad\u03c4\u03bf \u03b5\u03ac\u03bd",
        "option1": "\u0394\u03b5\u03bd \u03ad\u03c7\u03b5\u03b9 \u03bc\u03c0\u03b5\u03b9 \u03c4\u03bf \u03ba\u03bf\u03bc\u03bc\u03ac\u03c4\u03b9 \u03b3\u03b9\u03b1 \u03c0\u03ac\u03bd\u03c4\u03b1",
        "option2": "\u0388\u03c7\u03b5\u03b9 \u03bf\u03c1\u03b9\u03c3\u03b8\u03b5\u03af \u03af\u03b4\u03b9\u03bf \u03c7\u03c1\u03ce\u03bc\u03b1 \u03ba\u03b1\u03b9 \u03b3\u03b9\u03b1 \u03c4\u03b7\u03bd \u03c0\u03b5\u03c1\u03af\u03c0\u03c4\u03c9\u03c3\u03b7 \u03c0\u03bf\u03c5 \u03b5\u03af\u03bd\u03b1\u03b9 \u03c0\u03b1\u03c4\u03b7\u03bc\u03ad\u03bd\u03bf \u03c4\u03bf \u03ba\u03bf\u03c5\u03bc\u03c0\u03af \u03c0\u03b1\u03c4\u03b7\u03bc\u03ad\u03bd\u03bf \u03ba\u03b1\u03b9 \u03b3\u03b9\u03b1 \u03c4\u03b7\u03bd \u03c0\u03b5\u03c1\u03af\u03c0\u03c4\u03c9\u03c3\u03b7 \u03c0\u03bf\u03c5 \u03b4\u03b5\u03bd \u03b5\u03af\u03bd\u03b1\u03b9 \u03c0\u03b1\u03c4\u03b7\u03bc\u03ad\u03bd\u03bf",
        "option3": "\u03a4\u03bf \u03ba\u03bf\u03c5\u03bc\u03c0\u03af \u03ba\u03b1\u03b9 \u03c4\u03bf led \u03ad\u03c7\u03bf\u03c5\u03bd \u03b4\u03b7\u03bb\u03c9\u03b8\u03b5\u03af \u03c3\u03c4\u03bf \u03af\u03b4\u03b9\u03bf pin",
        "correct": "option0",
        "hint": null
    },
    {
        "question": "\u03a4\u03b9 \u03bb\u03ac\u03b8\u03bf\u03c2 \u03ad\u03c7\u03b5\u03b9 \u03b3\u03af\u03bd\u03b5\u03b9 \u03c3\u03c4\u03bf \u03c3\u03b5\u03bd\u03ac\u03c1\u03b9\u03bf \u03c4\u03b7\u03c2 \u03b4\u03b9\u03c0\u03bb\u03b1\u03bd\u03ae\u03c2 \u03b5\u03b9\u03ba\u03cc\u03bd\u03b1\u03c2;",
        "image": "img11.png",
        "option0": "\u0388\u03c7\u03b5\u03b9 \u03c7\u03c1\u03b7\u03c3\u03b9\u03bc\u03bf\u03c0\u03bf\u03b9\u03b7\u03b8\u03b5\u03af \u03bb\u03ac\u03b8\u03bf\u03c2 \u03c0\u03bb\u03b1\u03ba\u03af\u03b4\u03b9\u03bf \u03b5\u03bd\u03c4\u03bf\u03bb\u03ae\u03c2 \u03b3\u03b9\u03b1 \u03c4\u03bf \u03ba\u03bf\u03c5\u03bc\u03c0\u03af, \u03b8\u03b1 \u03c0\u03c1\u03ad\u03c0\u03b5\u03b9 \u03bd\u03b1 \u03c7\u03c1\u03b7\u03c3\u03b9\u03bc\u03bf\u03c0\u03bf\u03b9\u03b7\u03b8\u03b5\u03af \u03c4\u03bf \u03c0\u03bb\u03b1\u03ba\u03af\u03b4\u03b9\u03bf\u03c5 \u03c4\u03bf\u03c5 \u03ba\u03bf\u03c5\u03bc\u03c0\u03b9\u03bf\u03cd \u03c0\u03af\u03b5\u03c3\u03b7\u03c2 \u03ba\u03b1\u03b9 \u03cc\u03c7\u03b9 \u03b1\u03c6\u03ae\u03c2",
        "option1": "\u0398\u03b1 \u03c0\u03c1\u03ad\u03c0\u03b5\u03b9 \u03bd\u03b1 \u03c7\u03c1\u03b7\u03c3\u03b9\u03bc\u03bf\u03c0\u03bf\u03b9\u03b7\u03b8\u03b5\u03af \u03c4\u03bf \u03ba\u03bf\u03c5\u03bc\u03c0\u03af \u03b5\u03ac\u03bd \u03b1\u03bb\u03bb\u03b9\u03ce\u03c2 \u03ba\u03b1\u03b9 \u03cc\u03c7\u03b9 \u03c4\u03bf \u03c3\u03ba\u03ad\u03c4\u03bf\u03c2 \u03b5\u03ac\u03bd",
        "option2": "\u0388\u03c7\u03b5\u03b9 \u03bf\u03c1\u03b9\u03c3\u03b8\u03b5\u03af \u03af\u03b4\u03b9\u03bf \u03c7\u03c1\u03ce\u03bc\u03b1 \u03ba\u03b1\u03b9 \u03b3\u03b9\u03b1 \u03c4\u03b7\u03bd \u03c0\u03b5\u03c1\u03af\u03c0\u03c4\u03c9\u03c3\u03b7 \u03c0\u03bf\u03c5 \u03b5\u03af\u03bd\u03b1\u03b9 \u03c0\u03b1\u03c4\u03b7\u03bc\u03ad\u03bd\u03bf \u03c4\u03bf \u03ba\u03bf\u03c5\u03bc\u03c0\u03af \u03c0\u03b1\u03c4\u03b7\u03bc\u03ad\u03bd\u03bf \u03ba\u03b1\u03b9 \u03b3\u03b9\u03b1 \u03c4\u03b7\u03bd \u03c0\u03b5\u03c1\u03af\u03c0\u03c4\u03c9\u03c3\u03b7 \u03c0\u03bf\u03c5 \u03b4\u03b5\u03bd \u03b5\u03af\u03bd\u03b1\u03b9 \u03c0\u03b1\u03c4\u03b7\u03bc\u03ad\u03bd\u03bf",
        "option3": "\u03a4\u03bf \u03ba\u03bf\u03c5\u03bc\u03c0\u03af \u03ba\u03b1\u03b9 \u03c4\u03bf led \u03ad\u03c7\u03bf\u03c5\u03bd \u03b4\u03b7\u03bb\u03c9\u03b8\u03b5\u03af \u03c3\u03c4\u03bf \u03af\u03b4\u03b9\u03bf pin",
        "correct": "option0",
        "hint": null
    },
    {
        "question": "\u038c\u03c4\u03b1\u03bd \u03ba\u03ac\u03bd\u03bf\u03c5\u03bc\u03b5 \u03b1\u03bb\u03bb\u03b1\u03b3\u03ad\u03c2 \u03c3\u03c4\u03bf \u03c3\u03b5\u03bd\u03ac\u03c1\u03b9\u03bf \u03bc\u03b1\u03c2, \u03b4\u03b5\u03bd \u03c0\u03c1\u03ad\u03c0\u03b5\u03b9 \u03bd\u03b1 \u03be\u03b5\u03c7\u03bd\u03ac\u03bc\u03b5 \u03c4\u03bf upload",
        "image": "default.png",
        "option0": "\u03a3\u03c9\u03c3\u03c4\u03cc",
        "option1": "\u039b\u03ac\u03b8\u03bf\u03c2",
        "option2": "",
        "option3": "",
        "correct": "option0",
        "hint": null
    }
]